juham_watermeter/__init__.py
juham_watermeter/py.typed
juham_watermeter/watermeter_imgdiff.py
juham_watermeter/watermeter_ocr.py
juham_watermeter/watermeter_ts.py
juham_watermeter/webcamera.py
juham_watermeter-0.1.6.dist-info/licenses/LICENSE.rst
juham_watermeter-0.1.6.dist-info/METADATA
juham_watermeter-0.1.6.dist-info/WHEEL
juham_watermeter-0.1.6.dist-info/entry_points.txt
juham_watermeter-0.1.6.dist-info/top_level.txt
juham_watermeter-0.1.6.dist-info/RECORD
