Metadata-Version: 2.4
Name: juham-watermeter
Version: 0.1.6
Summary: Web-camera based watermeter for Juham
Author-email: J Meskanen <juham.api@gmail.com>
Maintainer-email: "J. Meskanen" <juham.api@gmail.com>
License-Expression: MIT
Project-URL: Homepage, https://gitlab.com/juham/juham
Project-URL: Bug Reports, https://gitlab.com/juham/juham
Project-URL: Funding, https://meskanen.com
Project-URL: Say Thanks!, http://meskanen.com
Project-URL: Source, https://gitlab.com/juham/juham
Keywords: object-oriented,plugin,framework,watermeter,home automation
Classifier: Development Status :: 3 - Alpha
Classifier: Intended Audience :: Developers
Classifier: Topic :: Software Development
Classifier: Programming Language :: Python :: 3.8
Requires-Python: >=3.8
License-File: LICENSE.rst
Requires-Dist: juham-automation>=0.2.11
Requires-Dist: numpy>=1.19
Requires-Dist: Pillow>=10.4.0
Requires-Dist: opencv-python-headless>=4.10.0
Requires-Dist: pytesseract>=0.3.13
Provides-Extra: dev
Requires-Dist: check-manifest; extra == "dev"
Dynamic: license-file
